scrcpy/__init__.py
scrcpy/client.py
scrcpy/const.py
scrcpy/control.py
scrcpy/scrcpy-server.jar
scrcpy-0.0.4.dist-info/LICENSE.txt
scrcpy-0.0.4.dist-info/WHEEL
scrcpy-0.0.4.dist-info/METADATA
scrcpy-0.0.4.dist-info/RECORD
